pandasai_chromadb/__init__.py
pandasai_chromadb/chroma.py
pandasai_chromadb-0.1.4.dist-info/LICENSE
pandasai_chromadb-0.1.4.dist-info/METADATA
pandasai_chromadb-0.1.4.dist-info/WHEEL
pandasai_chromadb-0.1.4.dist-info/RECORD
