Metadata-Version: 2.3
Name: pandasai-chromadb
Version: 0.1.4
Summary: ChromaDB integration for PandaAI
License: Proprietary
Author: Gabriele Venturi
Requires-Python: >=3.9,<3.12
Classifier: License :: Other/Proprietary License
Classifier: Programming Language :: Python :: 3
Classifier: Programming Language :: Python :: 3.9
Classifier: Programming Language :: Python :: 3.10
Classifier: Programming Language :: Python :: 3.11
Requires-Dist: chromadb (>=0.4.22,<0.5.0)
Requires-Dist: numpy (==1.23.2)
Requires-Dist: onnxruntime (>=1.14.1,<1.20)
Requires-Dist: pandasai (>=3.0.0b4)
Requires-Dist: pydantic (>=2.0.0,<3.0.0)
Project-URL: Documentation, https://docs.getpanda.ai/
Project-URL: Repository, https://github.com/sinaptik-ai/pandas-ai
